[
  {
    "id": "1",
    "title": "Workers United",
    "description": "A platform dedicated to uniting workers. [Description to be updated]",
    "tech": [
      "React",
      "Node.js"
    ],
    "link": "https://workersunited.eu",
    "image": "https://placehold.co/600x400/003B00/00FF41?text=Workers+United"
  },
  {
    "id": "2",
    "title": "Podovi",
    "description": "Flooring and interior design application. [Description to be updated]",
    "tech": [
      "Next.js",
      "Tailwind"
    ],
    "link": "https://podovi.online",
    "image": "https://placehold.co/600x400/003B00/00FF41?text=Podovi"
  }
]